docs/__init__.py
docs/quickstart/__init__.py
docs/quickstart/config.py
docs/quickstart/assessment/__init__.py
docs/quickstart/assessment/standalone_assessment.py
learnosity_sdk/__init__.py
learnosity_sdk/_version.py
learnosity_sdk/exceptions.py
learnosity_sdk/py.typed
learnosity_sdk/request/__init__.py
learnosity_sdk/request/dataapi.py
learnosity_sdk/request/init.py
learnosity_sdk/utils/__init__.py
learnosity_sdk/utils/lrnuuid.py
tests/__init__.py
tests/integration/__init__.py
tests/integration/test_dataapi.py
tests/unit/__init__.py
tests/unit/test_dataapi.py
tests/unit/test_init.py
tests/unit/test_sdk.py
tests/unit/test_uuid.py
learnosity_sdk-0.3.12.dist-info/LICENSE.md
learnosity_sdk-0.3.12.dist-info/METADATA
learnosity_sdk-0.3.12.dist-info/WHEEL
learnosity_sdk-0.3.12.dist-info/entry_points.txt
learnosity_sdk-0.3.12.dist-info/top_level.txt
learnosity_sdk-0.3.12.dist-info/RECORD
