Metadata-Version: 2.1
Name: learnosity_sdk
Version: 0.3.12
Summary: Learnosity SDK for Python
Home-page: https://github.com/Learnosity/learnosity-sdk-python
Author: Learnosity
Author-email: sdk@learnosity.com
License: Apache 2.0 license. See LICENSE.md for details.
License-File: LICENSE.md
Requires-Dist: requests>=2.21.0
Requires-Dist: certifi>=2024.07.04
Provides-Extra: dev
Requires-Dist: setuptools; extra == "dev"
Requires-Dist: twine; extra == "dev"
Requires-Dist: wheel; extra == "dev"
Provides-Extra: test
Requires-Dist: pre-commit; extra == "test"
Requires-Dist: pytest>=4.6.6; extra == "test"
Requires-Dist: pytest-cov>=2.8.1; extra == "test"
Requires-Dist: pytest-subtests; extra == "test"
Requires-Dist: pytest-randomly; extra == "test"
Requires-Dist: responses>=0.8.1; extra == "test"
Requires-Dist: types-requests; extra == "test"
Requires-Dist: types-Jinja2; extra == "test"
Requires-Dist: mypy; extra == "test"
Provides-Extra: quickstart
Requires-Dist: jinja2; extra == "quickstart"
